{
  "hash": "a44e4307",
  "configHash": "ed9facfa",
  "lockfileHash": "b2814a08",
  "browserHash": "f578344d",
  "optimized": {
    "vue": {
      "src": "../../../../node_modules/vue/dist/vue.runtime.esm-bundler.js",
      "file": "vue.js",
      "fileHash": "028f36a5",
      "needsInterop": false
    },
    "vitepress > @vue/devtools-api": {
      "src": "../../../../node_modules/@vue/devtools-api/dist/index.js",
      "file": "vitepress___@vue_devtools-api.js",
      "fileHash": "10cc04c5",
      "needsInterop": false
    },
    "vitepress > @vueuse/core": {
      "src": "../../../../node_modules/@vueuse/core/index.mjs",
      "file": "vitepress___@vueuse_core.js",
      "fileHash": "b76821ff",
      "needsInterop": false
    },
    "@theme/index": {
      "src": "../../../../node_modules/vitepress/dist/client/theme-default/index.js",
      "file": "@theme_index.js",
      "fileHash": "76e749d4",
      "needsInterop": false
    }
  },
  "chunks": {
    "chunk-QTXVCCMP": {
      "file": "chunk-QTXVCCMP.js"
    },
    "chunk-ONFHZ5OS": {
      "file": "chunk-ONFHZ5OS.js"
    }
  }
}